odoo/addons/project_task_code/README.rst
odoo/addons/project_task_code/__init__.py
odoo/addons/project_task_code/__manifest__.py
odoo/addons/project_task_code/hooks.py
odoo/addons/project_task_code/data/task_sequence.xml
odoo/addons/project_task_code/i18n/ar.po
odoo/addons/project_task_code/i18n/bg.po
odoo/addons/project_task_code/i18n/ca.po
odoo/addons/project_task_code/i18n/de.po
odoo/addons/project_task_code/i18n/el.po
odoo/addons/project_task_code/i18n/en.po
odoo/addons/project_task_code/i18n/es.po
odoo/addons/project_task_code/i18n/es_CR.po
odoo/addons/project_task_code/i18n/es_MX.po
odoo/addons/project_task_code/i18n/es_VE.po
odoo/addons/project_task_code/i18n/fi.po
odoo/addons/project_task_code/i18n/fr.po
odoo/addons/project_task_code/i18n/gl.po
odoo/addons/project_task_code/i18n/hr.po
odoo/addons/project_task_code/i18n/hr_HR.po
odoo/addons/project_task_code/i18n/hu.po
odoo/addons/project_task_code/i18n/it.po
odoo/addons/project_task_code/i18n/ja.po
odoo/addons/project_task_code/i18n/lt.po
odoo/addons/project_task_code/i18n/lv.po
odoo/addons/project_task_code/i18n/mk.po
odoo/addons/project_task_code/i18n/mn.po
odoo/addons/project_task_code/i18n/nl.po
odoo/addons/project_task_code/i18n/nl_NL.po
odoo/addons/project_task_code/i18n/pl.po
odoo/addons/project_task_code/i18n/project_task_code.pot
odoo/addons/project_task_code/i18n/pt.po
odoo/addons/project_task_code/i18n/pt_BR.po
odoo/addons/project_task_code/i18n/pt_PT.po
odoo/addons/project_task_code/i18n/ro.po
odoo/addons/project_task_code/i18n/sk.po
odoo/addons/project_task_code/i18n/sl.po
odoo/addons/project_task_code/i18n/sv.po
odoo/addons/project_task_code/i18n/tr.po
odoo/addons/project_task_code/i18n/uk.po
odoo/addons/project_task_code/i18n/zh_CN.po
odoo/addons/project_task_code/models/__init__.py
odoo/addons/project_task_code/models/project_task.py
odoo/addons/project_task_code/readme/CONFIGURE.rst
odoo/addons/project_task_code/readme/CONTRIBUTORS.rst
odoo/addons/project_task_code/readme/DESCRIPTION.rst
odoo12_addon_project_task_code-12.0.1.1.1.dist-info/METADATA
odoo12_addon_project_task_code-12.0.1.1.1.dist-info/WHEEL
odoo12_addon_project_task_code-12.0.1.1.1.dist-info/top_level.txt
odoo12_addon_project_task_code-12.0.1.1.1.dist-info/RECORD
